[
    {
      "id": 1,
      "itemName": "Drumstickmoringa",
      "itemPrice": "25AED / 250g",
      "itemImage": "item1.png"
    },
    {
      "id": 2,
      "itemName": "Pumpkin-disco",
      "itemPrice": "25AED / 250g",
      "itemImage": "item2.png"
    },
    {
      "id": 3,
      "itemName": "Green-peas",
      "itemPrice": "25AED / 250g",
      "itemImage": "item3.png"
    },

    {
      "id": 4,
      "itemName": "Drumstickmoringa",
      "itemPrice": "25AED / 250g",
      "itemImage": "item4.png"
    },

    {
      "id": 5,
      "itemName": "Pumpkin-disco",
      "itemPrice": "25AED / 250g",
      "itemImage": "item4.png"
    }

  ]
  